mkquartodocs/__init__.py
mkquartodocs/context.py
mkquartodocs/extension.py
mkquartodocs/logging.py
mkquartodocs/plugin.py
mkquartodocs/utils.py
mkquartodocs-0.7.0.dist-info/METADATA
mkquartodocs-0.7.0.dist-info/WHEEL
mkquartodocs-0.7.0.dist-info/entry_points.txt
mkquartodocs-0.7.0.dist-info/licenses/LICENSE
mkquartodocs-0.7.0.dist-info/RECORD
