Metadata-Version: 2.4
Name: mkquartodocs
Version: 0.7.0
Author-email: "J. Sebastian Paez" <jspaezp@users.noreply.github.com>
License-File: LICENSE
Requires-Python: <3.14,>=3.10
Requires-Dist: mkdocs>=1.6.1
Requires-Dist: pymdown-extensions
